neo/__init__.py
neo/models/__init__.py
neo/models/api_credentials.py
neo/models/pwd_credentials.py
neo/models/user.py
neo_sdk-0.1.0.dist-info/LICENSE
neo_sdk-0.1.0.dist-info/METADATA
neo_sdk-0.1.0.dist-info/WHEEL
neo_sdk-0.1.0.dist-info/top_level.txt
neo_sdk-0.1.0.dist-info/RECORD
