Metadata-Version: 2.1
Name: neo-sdk
Version: 0.1.0
Summary: SDK de conexão com o NEO Framework
Home-page: https://github.com/seuusuario/neo-sdk
Author: Luiz Carvalho
Author-email: dev@mtmtecnologia.com.br
Classifier: Programming Language :: Python :: 3
Classifier: License :: OSI Approved :: MIT License
Classifier: Operating System :: OS Independent
Requires-Python: >=3.11
License-File: LICENSE
Requires-Dist: requests>=2.26.0
